MANIFEST.in
README.rst
requirements.txt
setup.cfg
setup.py
cloudmesh/__init__.py
cloudmesh/cm_mesh.py
cloudmesh/cm_mongo.py
cloudmesh/cm_mongo2.py
cloudmesh/inventory.py
cloudmesh/version.py
cloudmesh.egg-info/PKG-INFO
cloudmesh.egg-info/SOURCES.txt
cloudmesh.egg-info/dependency_links.txt
cloudmesh.egg-info/entry_points.txt
cloudmesh.egg-info/pbr.json
cloudmesh.egg-info/requires.txt
cloudmesh.egg-info/top_level.txt
cloudmesh/accounting/AccountBaseClass.py
cloudmesh/accounting/GoldAccounting.py
cloudmesh/accounting/__init__.py
cloudmesh/accounting/metrics.py
cloudmesh/config/YAML.py
cloudmesh/config/__init__.py
cloudmesh/config/cm_config.py
cloudmesh/config/cm_init.py
cloudmesh/config/cm_keys.py
cloudmesh/config/cm_manage.py
cloudmesh/config/cm_me.py
cloudmesh/config/cm_projects.py
cloudmesh/config/openstack_grizzly_cloud.py
cloudmesh/experiment/__init__.py
cloudmesh/experiment/cm_experiment_db.py
cloudmesh/experiment/group.py
cloudmesh/experiment/group_usage.py
cloudmesh/experiment/model_group.py
cloudmesh/iaas/ComputeBaseType.py
cloudmesh/iaas/Ec2SecurityGroup.py
cloudmesh/iaas/__init__.py
cloudmesh/iaas/aws/__init__.py
cloudmesh/iaas/aws/cm_compute.py
cloudmesh/iaas/aws/queue/__init__.py
cloudmesh/iaas/aws/queue/celery.py
cloudmesh/iaas/aws/queue/tasks.py
cloudmesh/iaas/azure/__init__.py
cloudmesh/iaas/azure/cm_compute.py
cloudmesh/iaas/azure/queue/__init__.py
cloudmesh/iaas/azure/queue/celery.py
cloudmesh/iaas/azure/queue/tasks.py
cloudmesh/iaas/docker/__init__.py
cloudmesh/iaas/docker/queue/__init__.py
cloudmesh/iaas/ec2/__init__.py
cloudmesh/iaas/ec2/cm_compute.py
cloudmesh/iaas/ec2/queue/__init__.py
cloudmesh/iaas/ec2/queue/celery.py
cloudmesh/iaas/ec2/queue/tasks.py
cloudmesh/iaas/eucalyptus/__init__.py
cloudmesh/iaas/eucalyptus/eucalyptus.py
cloudmesh/iaas/opencirrus/__init__.py
cloudmesh/iaas/opencirrus/opencirrus.py
cloudmesh/iaas/openstack/__init__.py
cloudmesh/iaas/openstack/cm_compute.py
cloudmesh/iaas/openstack/cm_idm.py
cloudmesh/iaas/openstack/queue/__init__.py
cloudmesh/iaas/openstack/queue/celery.py
cloudmesh/iaas/openstack/queue/tasks.py
cloudmesh/iaas/vagrant/__init__.py
cloudmesh/iaas/vagrant/cm_vagrant.py
cloudmesh/image/__init__.py
cloudmesh/image/cm_image.py
