Metadata-Version: 1.1
Name: cloudmesh
Version: 2.2.9
Summary: A tool to enable federated management of multiple clouds including Azure, AWS, Eucalyptus, OpenStack
Home-page: http://github.org/cloudmesh/cloudmesh
Author: Cloudmesh Team
Author-email: laszewski@gmail.com
License: UNKNOWN
Platform: UNKNOWN
Classifier: Intended Audience :: Developers
Classifier: Intended Audience :: Education
Classifier: Intended Audience :: Science/Research
Classifier: Development Status :: 4 - Beta
Classifier: Intended Audience :: Developers
Classifier: License :: OSI Approved :: Apache Software License
Classifier: Operating System :: MacOS :: MacOS X
Classifier: Operating System :: POSIX :: Linux
Classifier: Programming Language :: Python :: 2.7
Classifier: Topic :: Database
Classifier: Topic :: Software Development :: Libraries :: Python Modules
Classifier: Topic :: Scientific/Engineering
Classifier: Topic :: System :: Clustering
Classifier: Topic :: System :: Distributed Computing
Classifier: Topic :: System :: Boot
Classifier: Topic :: System :: Systems Administration
Classifier: Framework :: Flask
Classifier: Environment :: OpenStack
